plone.patternslib-9.10.4-py3.13-nspkg.pth
plone/patternslib/__init__.py
plone/patternslib/configure.zcml
plone/patternslib/patternslib-preinit.js
plone/patternslib/setuphandlers.py
plone/patternslib/testing.py
plone/patternslib/browser/__init__.py
plone/patternslib/browser/configure.zcml
plone/patternslib/browser/demo/depends.pt
plone/patternslib/browser/demo/inject.pt
plone/patternslib/browser/demo/masonry.pt
plone/patternslib/browser/demo/switch.pt
plone/patternslib/profiles/default/metadata.xml
plone/patternslib/profiles/default/registry.xml
plone/patternslib/profiles/uninstall/registry.xml
plone/patternslib/static/0ff4d62150facee6b7de.png
plone/patternslib/static/14d740b6ee64510747b0.gif
plone/patternslib/static/456f618a6e4559de337b.jpg
plone/patternslib/static/527af3e99ad07977aac0.png
plone/patternslib/static/56d4c7ce2d3591a02107.gif
plone/patternslib/static/688bccf95583ddf2ba42.png
plone/patternslib/static/90c6de16dc3263413501.png
plone/patternslib/static/bundle.min.js
plone/patternslib/static/bundle.min.js.map
plone/patternslib/static/c07457739c183c845cac.png
plone/patternslib/static/modernizr.min.js
plone/patternslib/static/remote.min.js
plone/patternslib/static/remote.min.js.map
plone/patternslib/static/chunks/10088.57f96ab18ad9527a5758.min.js
plone/patternslib/static/chunks/10088.57f96ab18ad9527a5758.min.js.map
plone/patternslib/static/chunks/1012.5d1529a339d7df545fa5.min.js
plone/patternslib/static/chunks/1012.5d1529a339d7df545fa5.min.js.map
plone/patternslib/static/chunks/1073.4e0567f80c23bbe50e37.min.js
plone/patternslib/static/chunks/1073.4e0567f80c23bbe50e37.min.js.map
plone/patternslib/static/chunks/1086.6aa72ebef94c98f8442e.min.js
plone/patternslib/static/chunks/1086.6aa72ebef94c98f8442e.min.js.map
plone/patternslib/static/chunks/10997.a19b58adac4cc84f8319.min.js
plone/patternslib/static/chunks/10997.a19b58adac4cc84f8319.min.js.map
plone/patternslib/static/chunks/11025.1ced2f9a2f65c6b2e4c2.min.js
plone_patternslib-9.10.4.dist-info/licenses/LICENSE
plone_patternslib-9.10.4.dist-info/METADATA
plone_patternslib-9.10.4.dist-info/WHEEL
plone_patternslib-9.10.4.dist-info/entry_points.txt
plone_patternslib-9.10.4.dist-info/namespace_packages.txt
plone_patternslib-9.10.4.dist-info/top_level.txt
plone_patternslib-9.10.4.dist-info/RECORD
